searchmaude/FAERS.py
searchmaude/__init__.py
searchmaude/searchmaude.py
searchmaude-2.0.0.dist-info/LICENSE
searchmaude-2.0.0.dist-info/METADATA
searchmaude-2.0.0.dist-info/WHEEL
searchmaude-2.0.0.dist-info/entry_points.txt
searchmaude-2.0.0.dist-info/top_level.txt
searchmaude-2.0.0.dist-info/RECORD
